onecscripting/__init__.py
onecscripting/dbobj.py
onecscripting/errors.py
onecscripting/infobase.py
onecscripting/query.py
onecscripting/session.py
onecscripting/utils.py
onecscripting-1.0.1.dist-info/LICENSE
onecscripting-1.0.1.dist-info/METADATA
onecscripting-1.0.1.dist-info/WHEEL
onecscripting-1.0.1.dist-info/top_level.txt
onecscripting-1.0.1.dist-info/RECORD
