Metadata-Version: 2.1
Name: onecscripting
Version: 1.0.1
Summary: Purpose of this package is to simplify interaction with 1C databases through COMobjects using Python language.
Author-email: Vladislav Anisimov <pan.vlados.w@gmail.com>
Maintainer-email: Vladislav Anisimov <pan.vlados.w@gmail.com>
License: MIT License
Project-URL: repository, https://github.com/pan-vlados/onecscripting
Keywords: onec,1C,1c-enterprise,scripting,script,automation,COMObject
Classifier: Programming Language :: Python :: 3
Classifier: License :: OSI Approved :: MIT License
Classifier: Operating System :: Microsoft :: Windows
Requires-Python: >=3.8
License-File: LICENSE
Requires-Dist: pywin32 ; platform_system == "Windows"
Provides-Extra: dev
Requires-Dist: ruff ; extra == 'dev'
Requires-Dist: mypy ; extra == 'dev'
